nonebot_plugin_fhl-1.0.1.dist-info/METADATA
nonebot_plugin_fhl-1.0.1.dist-info/WHEEL
nonebot_plugin_fhl-1.0.1.dist-info/licenses/LICENSE
nonebot_plugin_fhl/__init__.py
nonebot_plugin_fhl/api.py
nonebot_plugin_fhl/config.py
nonebot_plugin_fhl/logic.py
nonebot_plugin_fhl/model.py
nonebot_plugin_fhl-1.0.1.dist-info/RECORD
